sflow/__init__.py
sflow/cpu.py
sflow/gpu.py
sflow/gpu0.py
sflow/gpu1.py
sflow/gpu2.py
sflow/gpu3.py
sflow/gpu4.py
sflow/gpu5.py
sflow/gpu6.py
sflow/gpu7.py
sflow/py.py
sflow/core/__init__.py
sflow/core/decay.py
sflow/core/defaults.py
sflow/core/functional_helper.py
sflow/core/ibind.py
sflow/core/iconst.py
sflow/core/icontext.py
sflow/core/icore.py
sflow/core/iextra.py
sflow/core/ifeeding.py
sflow/core/ifunctional.py
sflow/core/initializer.py
sflow/core/ioptimizer.py
sflow/core/ipatch.py
sflow/core/irandom.py
sflow/core/irecurrent.py
sflow/core/isummary.py
sflow/core/itrain.py
sflow/core/layertool.py
sflow/core/logg.py
sflow/core/optim.py
sflow/data/__init__.py
sflow/data/celeba.py
sflow/data/helen.py
sflow/data/celeb/__init__.py
sflow/data/celeb/attrpair.py
sflow/data/celeb/preprocess_align_face.py
sflow/data/coco/__init__.py
sflow/data/cyclegan/__init__.py
sflow/data/cyclegan/ae_photos.py
sflow/data/cyclegan/apple2orange.py
sflow/data/cyclegan/cezanne2photo.py
sflow/data/cyclegan/cityscapes.py
sflow/data/cyclegan/datasets.py
sflow/data/cyclegan/edges2handbags.py
sflow/data/cyclegan/edges2shoes.py
sflow/data/cyclegan/facades.py
sflow/data/cyclegan/horse2zebra.py
sflow/data/cyclegan/iphone2dslr_flower.py
sflow/data/cyclegan/maps.py
sflow/data/cyclegan/monet2photo.py
sflow/data/cyclegan/sketch2face.py
sflow/data/cyclegan/ukiyoe2photo.py
sflow/data/cyclegan/vangogh2photo.py
sflow/data/face/__init__.py
sflow/data/face/celeba.py
sflow/data/face/fer2013.py
sflow/data/face/frey.py
sflow/data/face/olivetti.py
sflow/data/face/umist.py
sflow/data/imagenet/__init__.py
sflow/data/imagenet/small.py
sflow/data/mnist/__init__.py
sflow/data/mnist/mnist.py
sflow/data/svhn/__init__.py
sflow/data/svhn/_convert_svhn_mat_to_record.py
sflow/data/svhn/svhn.py
sflow/data/wikiart/__init__.py
sflow/example/__init__.py
sflow/example/celeba_acgan.py
sflow/example/celeba_acgan_reconv.py
sflow/example/face_parse.py
sflow-1.8.0.1.dist-info/DESCRIPTION.rst
sflow-1.8.0.1.dist-info/METADATA
sflow-1.8.0.1.dist-info/RECORD
sflow-1.8.0.1.dist-info/WHEEL
sflow-1.8.0.1.dist-info/metadata.json
sflow-1.8.0.1.dist-info/top_level.txt
