Metadata-Version: 2.0
Name: sflow
Version: 1.8.0.1
Summary: super slim and simple syntatic sugar for Tensorflow
Home-page: https://github.com/dade-ai/sflow
Author: dade
Author-email: aiplore@gmail.com
License: MIT
Platform: UNKNOWN
Classifier: Development Status :: 3 - Alpha
Classifier: Intended Audience :: Developers
Classifier: License :: OSI Approved :: MIT License
Classifier: Programming Language :: Python :: 3.6
Requires-Dist: snipy
